addressify-0.0.1.dist-info/METADATA
addressify-0.0.1.dist-info/metadata.json
addressify-0.0.1.dist-info/top_level.txt
addressify-0.0.1.dist-info/WHEEL
addressify-0.0.1.dist-info/DESCRIPTION.rst
addressify-0.0.1.dist-info/RECORD
addressify/client.py
addressify/__init__.py
addressify/exceptions.py
