Metadata-Version: 2.0
Name: addressify
Version: 0.0.1
Summary: A Python wrapper around Addressify.com.au's APIs
Home-page: https://github.com/snowball-one/addressify
Author: Jonathan Moss
Author-email: open-sourc@snowballone.com.au
License: BSD
Keywords: wrapper,addresses,addressify,post,Australia
Platform: linux
Classifier: Environment :: Web Environment
Classifier: Intended Audience :: Developers
Classifier: License :: OSI Approved :: BSD License
Classifier: Operating System :: Unix
Classifier: Programming Language :: Python
Requires-Dist: requests (>=1.0.3)
